[
   {
      "id":"1",
      "tenmenu":"Abs",
      "hinhanhmenu":"https:\/\/cdn3.iconfinder.com\/data\/icons\/workouts\/500\/body-512.png"
   },
   {
      "id":"2",
      "tenmenu":"Arms",
      "hinhanhmenu":"https:\/\/img0.etsystatic.com\/201\/0\/13221305\/il_570xN.1210639720_3wp5.jpg"
   },
   {
      "id":"3",
      "tenmenu":"Butt",
      "hinhanhmenu":"https:\/\/d30y9cdsu7xlg0.cloudfront.net\/png\/356030-200.png"
   },
   {
      "id":"4",
      "tenmenu":"Legs",
      "hinhanhmenu":"https:\/\/image.freepik.com\/free-icon\/male-legs-couple_318-46979.jpg"
   },
   {
      "id":"5",
      "tenmenu":"Back Muscle",
      "hinhanhmenu":"https:\/\/cdn3.iconfinder.com\/data\/icons\/workouts\/500\/muscle-512.png"
   },
   {
      "id":"6",
      "tenmenu":"Chest",
      "hinhanhmenu":"https:\/\/maxcdn.icons8.com\/Share\/icon\/Sports\/\/chest1600.png"
   }
]